sleap_roots/__init__.py
sleap_roots/angle.py
sleap_roots/bases.py
sleap_roots/convhull.py
sleap_roots/ellipse.py
sleap_roots/lengths.py
sleap_roots/networklength.py
sleap_roots/points.py
sleap_roots/scanline.py
sleap_roots/series.py
sleap_roots/summary.py
sleap_roots/tips.py
sleap_roots/trait_pipelines.py
sleap_roots-0.1.4.dist-info/licenses/LICENSE
sleap_roots-0.1.4.dist-info/METADATA
sleap_roots-0.1.4.dist-info/WHEEL
sleap_roots-0.1.4.dist-info/top_level.txt
sleap_roots-0.1.4.dist-info/RECORD
