Metadata-Version: 2.4
Name: sleap-roots
Version: 0.1.4
Summary: Analysis tools for SLEAP-based plant root phenotyping.
Author-email: Elizabeth Berrigan <eberrigan@salk.edu>, Lin Wang <linwang@salk.edu>, Talmo Pereira <talmo@salk.edu>
License: BSD-3-Clause
Project-URL: Homepage, https://github.com/talmolab/sleap-roots
Project-URL: Repository, https://github.com/talmolab/sleap-roots
Keywords: sleap,plants,roots,phenotyping
Classifier: Programming Language :: Python :: 3.7
Classifier: Programming Language :: Python :: 3.8
Classifier: Programming Language :: Python :: 3.9
Classifier: Programming Language :: Python :: 3.10
Classifier: Programming Language :: Python :: 3.11
Requires-Python: >=3.7
License-File: LICENSE
Requires-Dist: numpy
Requires-Dist: h5py
Requires-Dist: attrs
Requires-Dist: pandas
Requires-Dist: matplotlib
Requires-Dist: seaborn
Requires-Dist: sleap-io>=0.0.11
Requires-Dist: scikit-image
Requires-Dist: shapely
Provides-Extra: dev
Requires-Dist: pytest; extra == "dev"
Requires-Dist: pytest-cov; extra == "dev"
Requires-Dist: black; extra == "dev"
Requires-Dist: pydocstyle; extra == "dev"
Requires-Dist: toml; extra == "dev"
Requires-Dist: twine; extra == "dev"
Requires-Dist: build; extra == "dev"
Dynamic: license-file
